copilot_platforms_sdk/__init__.py
copilot_platforms_sdk/api_client.py
copilot_platforms_sdk/configuration.py
copilot_platforms_sdk/exceptions.py
copilot_platforms_sdk/rest.py
copilot_platforms_sdk/schemas.py
copilot_platforms_sdk/apis/__init__.py
copilot_platforms_sdk/apis/path_to_api.py
copilot_platforms_sdk/apis/tag_to_api.py
copilot_platforms_sdk/apis/paths/__init__.py
copilot_platforms_sdk/apis/paths/channel_file.py
copilot_platforms_sdk/apis/paths/client.py
copilot_platforms_sdk/apis/paths/client_id.py
copilot_platforms_sdk/apis/paths/company.py
copilot_platforms_sdk/apis/paths/company_id.py
copilot_platforms_sdk/apis/paths/custom_fields.py
copilot_platforms_sdk/apis/paths/file.py
copilot_platforms_sdk/apis/paths/form.py
copilot_platforms_sdk/apis/paths/form_id.py
copilot_platforms_sdk/apis/paths/form_response.py
copilot_platforms_sdk/apis/tags/__init__.py
copilot_platforms_sdk/apis/tags/copilot_api.py
copilot_platforms_sdk/model/__init__.py
copilot_platforms_sdk/model/api_client_item.py
copilot_platforms_sdk/model/api_company_item.py
copilot_platforms_sdk/model/api_custom_field.py
copilot_platforms_sdk/model/api_custom_field_item.py
copilot_platforms_sdk/model/api_custom_field_item_config.py
copilot_platforms_sdk/model/api_custom_field_option.py
copilot_platforms_sdk/model/api_form_item.py
copilot_platforms_sdk/model/api_form_response_input.py
copilot_platforms_sdk/model/api_form_response_item.py
copilot_platforms_sdk/model/api_list.py
copilot_platforms_sdk/model/auth_request_permissions.py
copilot_platforms_sdk/model/constants_api_object.py
copilot_platforms_sdk/model/constants_view_mode.py
copilot_platforms_sdk/model/dispatcher_error.py
copilot_platforms_sdk/model/files_create_file_input.py
copilot_platforms_sdk/model/files_fields.py
copilot_platforms_sdk/model/files_file.py
copilot_platforms_sdk/model/intake_form_responses_intake_form_request_input.py
copilot_platforms_sdk/models/__init__.py
copilot_platforms_sdk/paths/__init__.py
copilot_platforms_sdk-1.0.0.dist-info/METADATA
copilot_platforms_sdk-1.0.0.dist-info/WHEEL
copilot_platforms_sdk-1.0.0.dist-info/top_level.txt
copilot_platforms_sdk-1.0.0.dist-info/RECORD
